LICENSE.txt
MANIFEST.in
README.md
setup.py
giwyn/__init__.py
giwyn/main.py
giwyn.egg-info/PKG-INFO
giwyn.egg-info/SOURCES.txt
giwyn.egg-info/dependency_links.txt
giwyn.egg-info/entry_points.txt
giwyn.egg-info/requires.txt
giwyn.egg-info/top_level.txt
giwyn/lib/__init__.py
giwyn/lib/scan.py
giwyn/lib/config/__init__.py
giwyn/lib/config/config.py
giwyn/lib/gitconf/__init__.py
giwyn/lib/gitconf/commands.py
giwyn/lib/gitconf/git_o.py
giwyn/lib/settings/__init__.py
giwyn/lib/settings/settings.py