Metadata-Version: 1.1
Name: giwyn
Version: 0.3.1
Summary: A simple command to manage all your git clones
Home-page: http://github.com/k0pernicus/giwyn
Author: k0pernicus
Author-email: antonin.carette@gmail.com
License: GnuGPL
Keywords: git development versioning package
Platform: UNKNOWN
Classifier: Intended Audience :: Developers
Classifier: Topic :: Software Development :: Build Tools
Classifier: Programming Language :: Python :: 3.4
Classifier: Environment :: Console
